mycttestsdk/__init__.py
mycttestsdk/run.py
mycttestsdk-0.1.2.dist-info/LICENSE
mycttestsdk-0.1.2.dist-info/METADATA
mycttestsdk-0.1.2.dist-info/WHEEL
mycttestsdk-0.1.2.dist-info/top_level.txt
mycttestsdk-0.1.2.dist-info/RECORD
