Metadata-Version: 2.1
Name: mycttestsdk
Version: 0.1.2
Summary: Used for integration with Application monitoring systems
License-File: LICENSE
